amethyst/__init__.py
amethyst/amy.py
amethyst/app.py
amethyst/color_scheme.py
amethyst/config.py
amethyst/consts.py
amethyst/face.py
amethyst/gem.py
amethyst/gui_common.py
amethyst/gui_pyglet.py
amethyst/gui_pyqt.py
amethyst/icons.py
amethyst/input.py
amethyst/main.py
assets/materialdesignicons.woff
resources/color_schemes/solarized_dark.yml
resources/default_config.yml
resources/modules/greetings_animal/animals.json
resources/modules/greetings_animal/animals.py
resources/modules/greetings_animal/greetings.py
resources/modules/sway_workspace_switcher.py
amethyst-0.1.3.dist-info/entry_points.txt
amethyst-0.1.3.dist-info/LICENSE
amethyst-0.1.3.dist-info/WHEEL
amethyst-0.1.3.dist-info/METADATA
amethyst-0.1.3.dist-info/RECORD
